config_segregate/__init__.py
config_segregate/core.py
config_segregate/readers.py
config_segregate/writers.py
config_segregate-0.1.0.dist-info/LICENSE
config_segregate-0.1.0.dist-info/METADATA
config_segregate-0.1.0.dist-info/WHEEL
config_segregate-0.1.0.dist-info/RECORD
