Metadata-Version: 2.1
Name: config-segregate
Version: 0.1.0
Summary: Config-Segregate simplifies Config management by enabling efficient, customizable configurations through classifier-based loading.
Home-page: https://github.com/ross-tsenov/config-segregate
License: MIT
Author: Ross Tsenov
Author-email: ross.tsenov@github.com
Maintainer: Ross Tsenov
Maintainer-email: ross.tsenov@github.com
Requires-Python: >=3.8.1,<4.0.0
Classifier: License :: OSI Approved :: MIT License
Classifier: Programming Language :: Python :: 3
Classifier: Programming Language :: Python :: 3.9
Classifier: Programming Language :: Python :: 3.10
Classifier: Programming Language :: Python :: 3.11
Classifier: Programming Language :: Python :: 3.12
Provides-Extra: all
Provides-Extra: toml
Requires-Dist: toml (>=0.10.2,<0.11.0) ; extra == "all" or extra == "toml"
Project-URL: Documentation, https://github.com/ross-tsenov/config-segregate/tree/main/docs/
Project-URL: Repository, https://github.com/ross-tsenov/config-segregate
